minitap_meta/__init__.py
minitap-0.1.1.dist-info/METADATA
minitap-0.1.1.dist-info/WHEEL
minitap-0.1.1.dist-info/top_level.txt
minitap-0.1.1.dist-info/RECORD
