Metadata-Version: 2.4
Name: minitap
Version: 0.1.1
Summary: PyPI meta-package for accessible packages published by Minitap
Project-URL: Homepage, https://minitap.ai/
Project-URL: Source, https://github.com/minitap-ai/mobile-use
Requires-Python: >=3.12
Requires-Dist: minitap-mobile-use<3.0.0,>=2.0.0
